README.rst
setup.py
bin/gpip
bin/gpip.cmd
src/gpip/__init__.py
src/gpip/tools.py
src/gpip.egg-info/PKG-INFO
src/gpip.egg-info/SOURCES.txt
src/gpip.egg-info/dependency_links.txt
src/gpip.egg-info/requires.txt
src/gpip.egg-info/top_level.txt
src/gpip/_cli/__init__.py
src/gpip/_cli/cli.py
src/gpip/_cli/commands/__init__.py
src/gpip/_cli/commands/get.py
src/gpip/_cli/commands/install.py
src/gpip/_cli/commands/version.py
src/gpip/_cli/util/__init__.py
src/gpip/_cli/util/run.py
src/gpip/_internal/__init__.py
src/gpip/_internal/builder.py
src/gpip/_internal/downloader.py
src/gpip/_internal/exceptions.py
src/gpip/_internal/installer.py
src/gpip/_internal/repository.py
test/test_cli.py
test/test_downloader.py
test/test_install.py
test/test_repository.py